datasparkler/src/__init__.py
datasparkler/src/main.py
datasparkler/src/my_data_import_lib.py
datasparkler/src/my_data_preprocessing_lib.py
datasparkler/src/my_data_saving_lib.py
datasparkler/src/my_visualization_lib.py
datasparkler/tests/test_data_import.py
datasparkler/tests/test_data_preprocessing.py
datasparkler/tests/test_data_visualization.py
datasparkler-2.0.0.dist-info/LICENSE
datasparkler-2.0.0.dist-info/METADATA
datasparkler-2.0.0.dist-info/WHEEL
datasparkler-2.0.0.dist-info/top_level.txt
datasparkler-2.0.0.dist-info/RECORD
