Metadata-Version: 2.1
Name: datasparkler
Version: 2.0.0
Summary: A data preprocessing library that enables the cleaning and visualization of data
Author-email: Ainembabazi Withus <ainembabaziwithus@gmail.com>
Project-URL: Homepage, https://github.com/AinzWithus/DataPreprocessingLibrary.git
Classifier: Programming Language :: Python :: 3
Classifier: License :: OSI Approved :: MIT License
Classifier: Operating System :: OS Independent
Requires-Python: >=3.8
License-File: LICENSE
